odoo/addons/sale_subscription_disable_tokenization/LICENSE
odoo/addons/sale_subscription_disable_tokenization/README.rst
odoo/addons/sale_subscription_disable_tokenization/__init__.py
odoo/addons/sale_subscription_disable_tokenization/__manifest__.py
odoo/addons/sale_subscription_disable_tokenization/images/screen.png
odoo/addons/sale_subscription_disable_tokenization/models/__init__.py
odoo/addons/sale_subscription_disable_tokenization/models/payment_provider.py
odoo/addons/sale_subscription_disable_tokenization/readme/CONTRIBUTORS.md
odoo/addons/sale_subscription_disable_tokenization/readme/DESCRIPTION.md
odoo/addons/sale_subscription_disable_tokenization/readme/USAGE.md
odoo/addons/sale_subscription_disable_tokenization/static/description/icon.png
odoo/addons/sale_subscription_disable_tokenization/static/description/index.html
odoo/addons/sale_subscription_disable_tokenization/tests/TEST_INSTRUCTIONS.rst
odoo_addon_sale_subscription_disable_tokenization-18.0.1.0.0.dist-info/METADATA
odoo_addon_sale_subscription_disable_tokenization-18.0.1.0.0.dist-info/WHEEL
odoo_addon_sale_subscription_disable_tokenization-18.0.1.0.0.dist-info/top_level.txt
odoo_addon_sale_subscription_disable_tokenization-18.0.1.0.0.dist-info/RECORD
