Metadata-Version: 2.1
Name: odoo-addon-sale_subscription_disable_tokenization
Version: 18.0.1.0.0
Requires-Python: >=3.10
Requires-Dist: odoo==18.0.*
Summary: Do not force payment tokenization for order with subscriptions.
Home-page: https://github.com/Mint-system/
License: OPL-1
Author: Mint System GmbH
Classifier: Programming Language :: Python
Classifier: Framework :: Odoo
Classifier: Framework :: Odoo :: 18.0
